{"match_id":"78bb223a-7f33-4ea0-9c70-4e2e73dfc153.nakama-0","map_id":"AmbroseValley","date":"February 10","players":{"0":{"id":"a573ce12-43ad-4fe6-946f-946cc4240d99","isBot":false}},"events":[[0,0,"Position",-107.6,-362.2],[20,0,"Position",-106.7,-339.4],[25,0,"Position",-103.3,-309.6],[30,0,"Position",-131.7,-311.1],[35,0,"Position",-147.7,-324.8],[40,0,"Position",-153.3,-338.1],[44,0,"BotKill",-150.9,-335.1],[47,0,"Loot",-156.4,-332.1],[48,0,"Loot",-156.4,-332.1],[50,0,"Position",-165.1,-336.6],[55,0,"Position",-171.4,-333.5],[60,0,"Loot",-170.5,-340.8],[60,0,"Position",-170.5,-339.7],[65,0,"Position",-179.0,-335.8],[70,0,"Position",-199.9,-331.9],[76,0,"Position",-212.1,-322.7],[81,0,"Position",-221.6,-321.2],[86,0,"Loot",-222.3,-321.5],[91,0,"Position",-213.8,-324.9],[96,0,"Position",-219.1,-330.2],[98,0,"Loot",-219.2,-330.1],[101,0,"Position",-215.4,-327.8],[106,0,"Position",-212.8,-324.5],[111,0,"Position",-213.3,-326.1],[116,0,"Position",-214.1,-321.7],[126,0,"Position",-212.5,-326.8],[131,0,"Position",-208.2,-322.2],[131,0,"BotKill",-207.6,-321.5],[136,0,"Loot",-206.4,-320.3],[136,0,"Loot",-206.4,-320.3],[136,0,"Loot",-206.4,-320.3],[141,0,"Position",-192.6,-318.9],[142,0,"Loot",-191.3,-318.6],[146,0,"Position",-184.2,-307.3],[151,0,"Position",-166.8,-326.4],[157,0,"Loot",-167.3,-329.9],[161,0,"Position",-171.5,-311.1],[166,0,"Position",-142.7,-309.6],[171,0,"Position",-124.9,-284.1],[176,0,"Position",-124.7,-275.1],[181,0,"Position",-127.3,-259.1],[186,0,"Position",-147.5,-253.9],[191,0,"Position",-161.1,-246.1],[196,0,"Position",-165.2,-229.6],[201,0,"Position",-168.8,-212.7],[206,0,"Position",-169.2,-195.5],[211,0,"Position",-162.7,-179.3],[216,0,"Position",-152.9,-170.4],[221,0,"Position",-137.6,-149.6],[226,0,"Position",-121.2,-134.4],[231,0,"Position",-106.2,-120.5],[240,0,"BotKill",-107.5,-121.1],[241,0,"Position",-107.7,-120.0],[246,0,"Position",-99.2,-93.3],[251,0,"Position",-93.0,-92.4],[256,0,"BotKill",-92.5,-93.0],[262,0,"Position",-78.8,-98.4],[267,0,"Position",-59.4,-82.2],[272,0,"Position",-58.5,-79.5],[272,0,"Loot",-58.5,-79.5],[273,0,"Loot",-58.5,-79.5],[277,0,"Position",-53.0,-76.1],[280,0,"Loot",-49.7,-66.8],[280,0,"Loot",-49.7,-66.8],[282,0,"Position",-49.4,-65.6],[286,0,"BotKilled",-57.6,-58.8],[287,0,"Position",-57.6,-58.8]]}